xraylabtool/__init__.py
xraylabtool/cli.py
xraylabtool/constants.py
xraylabtool/exceptions.py
xraylabtool/logging_utils.py
xraylabtool/py.typed
xraylabtool/typing_extensions.py
xraylabtool/utils.py
xraylabtool/analysis/__init__.py
xraylabtool/analysis/comparator.py
xraylabtool/calculators/__init__.py
xraylabtool/calculators/core.py
xraylabtool/calculators/derived_quantities.py
xraylabtool/cleanup/__init__.py
xraylabtool/data/AtomicScatteringFactor/C.nff
xraylabtool/data/AtomicScatteringFactor/ac.nff
xraylabtool/data/AtomicScatteringFactor/ag.nff
xraylabtool/data/AtomicScatteringFactor/al.nff
xraylabtool/data/AtomicScatteringFactor/ar.nff
xraylabtool/data/AtomicScatteringFactor/as.nff
xraylabtool/data/AtomicScatteringFactor/at.nff
xraylabtool/data/AtomicScatteringFactor/au.nff
xraylabtool/data/AtomicScatteringFactor/b.nff
xraylabtool/data/AtomicScatteringFactor/ba.nff
xraylabtool/data/AtomicScatteringFactor/be.nff
xraylabtool/data/AtomicScatteringFactor/bi.nff
xraylabtool/data/AtomicScatteringFactor/br.nff
xraylabtool/data/AtomicScatteringFactor/c.nff
xraylabtool/data/AtomicScatteringFactor/ca.nff
xraylabtool/data/AtomicScatteringFactor/cd.nff
xraylabtool/data/AtomicScatteringFactor/ce.nff
xraylabtool/data/AtomicScatteringFactor/cl.nff
xraylabtool/data/AtomicScatteringFactor/co.nff
xraylabtool/data/AtomicScatteringFactor/cr.nff
xraylabtool/data/AtomicScatteringFactor/cs.nff
xraylabtool/data/AtomicScatteringFactor/cu.nff
xraylabtool/data/AtomicScatteringFactor/dy.nff
xraylabtool/data/AtomicScatteringFactor/er.nff
xraylabtool/data/AtomicScatteringFactor/eu.nff
xraylabtool/data/AtomicScatteringFactor/f.nff
xraylabtool/data/AtomicScatteringFactor/fe.nff
xraylabtool/data/AtomicScatteringFactor/fr.nff
xraylabtool/data/AtomicScatteringFactor/ga.nff
xraylabtool/data/AtomicScatteringFactor/gd.nff
xraylabtool/data/AtomicScatteringFactor/ge.nff
xraylabtool/data/AtomicScatteringFactor/h.nff
xraylabtool/data/AtomicScatteringFactor/he.nff
xraylabtool-0.3.0.dist-info/licenses/LICENSE
xraylabtool-0.3.0.dist-info/METADATA
xraylabtool-0.3.0.dist-info/WHEEL
xraylabtool-0.3.0.dist-info/entry_points.txt
xraylabtool-0.3.0.dist-info/top_level.txt
xraylabtool-0.3.0.dist-info/RECORD
