Metadata-Version: 2.4
Name: xraylabtool
Version: 0.3.0
Summary: Ultra-fast Python package for X-ray optical properties calculation with CXRO/NIST data, CLI tools, and synchrotron applications
Author-email: Wei Chen <wchen@anl.gov>
Maintainer-email: Wei Chen <wchen@anl.gov>
License-Expression: MIT
Project-URL: Homepage, https://github.com/imewei/pyXRayLabTool
Project-URL: Documentation, https://pyxraylabtool.readthedocs.io
Project-URL: Repository, https://github.com/imewei/pyXRayLabTool
Project-URL: Source Code, https://github.com/imewei/pyXRayLabTool
Project-URL: Bug Tracker, https://github.com/imewei/pyXRayLabTool/issues
Project-URL: Changelog, https://github.com/imewei/pyXRayLabTool/blob/main/CHANGELOG.md
Project-URL: CLI Reference, https://pyxraylabtool.readthedocs.io/en/latest/cli_guide.html
Project-URL: Shell Completion Guide, https://pyxraylabtool.readthedocs.io/en/latest/completion_guide.html
Project-URL: Discussions, https://github.com/imewei/pyXRayLabTool/discussions
Project-URL: Release Notes, https://github.com/imewei/pyXRayLabTool/releases
Keywords: xray,x-ray,xrd,xrr,saxs,crystallography,diffraction,scattering,synchrotron,beamline,optics,reflectometry,absorption,spectroscopy,materials-science,condensed-matter,physics,chemistry,nanotechnology,thin-films,multilayers,nanostructures,characterization,cxro,nist,atomic-scattering-factors,optical-constants,refractive-index,critical-angle,attenuation-length,form-factors,dispersion,absorption-coefficient,high-performance,vectorized,batch-processing,parallel-processing,scientific-computing,
Classifier: Development Status :: 5 - Production/Stable
Classifier: Intended Audience :: Science/Research
Classifier: Intended Audience :: Developers
Classifier: Intended Audience :: Education
Classifier: Intended Audience :: Manufacturing
Classifier: Intended Audience :: Healthcare Industry
Classifier: Operating System :: OS Independent
Classifier: Operating System :: POSIX :: Linux
Classifier: Operating System :: MacOS
Classifier: Operating System :: Microsoft :: Windows
Classifier: Programming Language :: Python :: 3
Classifier: Programming Language :: Python :: 3.12
Classifier: Programming Language :: Python :: 3.13
Classifier: Programming Language :: Python :: Implementation :: CPython
Classifier: Topic :: Scientific/Engineering :: Physics
Classifier: Topic :: Scientific/Engineering :: Chemistry
Classifier: Topic :: Scientific/Engineering :: Information Analysis
Classifier: Topic :: Scientific/Engineering :: Visualization
Classifier: Topic :: Scientific/Engineering
Classifier: Topic :: Software Development :: Libraries :: Python Modules
Classifier: Topic :: System :: Shells
Classifier: Topic :: Utilities
Classifier: Environment :: Console
Classifier: Environment :: Web Environment
Classifier: Natural Language :: English
Classifier: Typing :: Typed
Requires-Python: >=3.12
License-File: LICENSE
Requires-Dist: numpy>=2.3.5
Requires-Dist: pandas>=2.3.3
Requires-Dist: scipy>=1.16.3
Requires-Dist: matplotlib>=3.10.8
Requires-Dist: mendeleev>=1.1.0
Requires-Dist: tqdm>=4.67.1
Requires-Dist: psutil>=7.1.3
Provides-Extra: dev
Requires-Dist: pytest>=9.0.2; extra == "dev"
Requires-Dist: pytest-cov>=7.0.0; extra == "dev"
Requires-Dist: pytest-benchmark>=5.2.3; extra == "dev"
Requires-Dist: pytest-xdist>=3.8.0; extra == "dev"
Requires-Dist: pytest-timeout>=2.4.0; extra == "dev"
Requires-Dist: black>=25.12.0; extra == "dev"
Requires-Dist: flake8>=7.3.0; extra == "dev"
Requires-Dist: mypy>=1.19.0; extra == "dev"
Requires-Dist: ruff>=0.14.9; extra == "dev"
Requires-Dist: isort>=7.0.0; extra == "dev"
Requires-Dist: bandit[toml]>=1.9.2; extra == "dev"
Requires-Dist: pbr>=7.0.3; extra == "dev"
Requires-Dist: safety>=2.3.4; extra == "dev"
Requires-Dist: pandas-stubs>=2.3.3.251201; extra == "dev"
Requires-Dist: types-tqdm>=4.67.0.20250809; extra == "dev"
Requires-Dist: types-psutil>=7.1.3.20251202; extra == "dev"
Requires-Dist: pre-commit>=4.5.0; extra == "dev"
Requires-Dist: codecov>=2.1.13; extra == "dev"
Requires-Dist: build>=1.0.0; extra == "dev"
Requires-Dist: twine>=4.0.0; extra == "dev"
Provides-Extra: docs
Requires-Dist: sphinx>=8.2.3; extra == "docs"
Requires-Dist: furo>=2025.9.25; extra == "docs"
Requires-Dist: sphinx-autodoc-typehints>=3.5.2; extra == "docs"
Requires-Dist: sphinx-copybutton>=0.5.2; extra == "docs"
Requires-Dist: sphinx-design>=0.6.1; extra == "docs"
Requires-Dist: sphinx-tabs>=3.4.7; extra == "docs"
Requires-Dist: sphinx-togglebutton>=0.3.2; extra == "docs"
Requires-Dist: myst-parser>=4.0.1; extra == "docs"
Requires-Dist: sphinxcontrib-napoleon>=0.7; extra == "docs"
Requires-Dist: doc8>=2.0.0; extra == "docs"
Requires-Dist: rstcheck>=6.2.5; extra == "docs"
Requires-Dist: Pygments>=2.19.2; extra == "docs"
Requires-Dist: docutils>=0.21.2; extra == "docs"
Provides-Extra: test
Requires-Dist: pytest>=9.0.2; extra == "test"
Requires-Dist: pytest-cov>=7.0.0; extra == "test"
Requires-Dist: pytest-benchmark>=5.2.3; extra == "test"
Requires-Dist: pytest-xdist>=3.8.0; extra == "test"
Requires-Dist: pytest-timeout>=2.4.0; extra == "test"
Provides-Extra: lint
Requires-Dist: black>=25.12.0; extra == "lint"
Requires-Dist: flake8>=7.3.0; extra == "lint"
Requires-Dist: mypy>=1.19.0; extra == "lint"
Requires-Dist: ruff>=0.14.9; extra == "lint"
Requires-Dist: isort>=7.0.0; extra == "lint"
Requires-Dist: bandit[toml]>=1.9.2; extra == "lint"
Requires-Dist: safety>=2.3.4; extra == "lint"
Requires-Dist: pandas-stubs>=2.3.3.251201; extra == "lint"
Requires-Dist: types-tqdm>=4.67.0.20250809; extra == "lint"
Requires-Dist: types-psutil>=7.1.3.20251202; extra == "lint"
Provides-Extra: export
Requires-Dist: openpyxl>=3.1.5; extra == "export"
Requires-Dist: seaborn>=0.13.2; extra == "export"
Requires-Dist: plotly>=6.5.0; extra == "export"
Requires-Dist: jinja2>=3.1.6; extra == "export"
Provides-Extra: api
Requires-Dist: fastapi>=0.124.0; extra == "api"
Requires-Dist: uvicorn[standard]>=0.38.0; extra == "api"
Requires-Dist: python-multipart>=0.0.20; extra == "api"
Requires-Dist: PyJWT[crypto]>=2.10.0; extra == "api"
Requires-Dist: passlib[bcrypt]>=1.7.4; extra == "api"
Requires-Dist: python-dateutil>=2.9.0.post0; extra == "api"
Provides-Extra: analysis
Requires-Dist: scikit-learn>=1.7.2; extra == "analysis"
Requires-Dist: scipy>=1.16.3; extra == "analysis"
Requires-Dist: statsmodels>=0.14.6; extra == "analysis"
Provides-Extra: perf
Requires-Dist: memory-profiler>=0.61.0; extra == "perf"
Requires-Dist: line-profiler>=5.0.0; extra == "perf"
Requires-Dist: py-spy>=0.4.1; extra == "perf"
Requires-Dist: PySide6>=6.10.1; extra == "perf"
Provides-Extra: gui
Requires-Dist: PySide6>=6.10.1; extra == "gui"
Provides-Extra: all
Requires-Dist: pytest>=9.0.2; extra == "all"
Requires-Dist: pytest-cov>=7.0.0; extra == "all"
Requires-Dist: pytest-benchmark>=5.2.3; extra == "all"
Requires-Dist: pytest-xdist>=3.8.0; extra == "all"
Requires-Dist: pytest-timeout>=2.4.0; extra == "all"
Requires-Dist: black>=25.12.0; extra == "all"
Requires-Dist: flake8>=7.3.0; extra == "all"
Requires-Dist: mypy>=1.19.0; extra == "all"
Requires-Dist: ruff>=0.14.9; extra == "all"
Requires-Dist: isort>=7.0.0; extra == "all"
Requires-Dist: bandit[toml]>=1.9.2; extra == "all"
Requires-Dist: pbr>=7.0.3; extra == "all"
Requires-Dist: safety>=2.3.4; extra == "all"
Requires-Dist: pandas-stubs>=2.3.3.251201; extra == "all"
Requires-Dist: types-tqdm>=4.67.0.20250809; extra == "all"
Requires-Dist: types-psutil>=7.1.3.20251202; extra == "all"
Requires-Dist: pre-commit>=4.5.0; extra == "all"
Requires-Dist: codecov>=2.1.13; extra == "all"
Requires-Dist: build>=1.0.0; extra == "all"
Requires-Dist: twine>=4.0.0; extra == "all"
Requires-Dist: sphinx>=8.2.3; extra == "all"
Requires-Dist: furo>=2025.9.25; extra == "all"
Requires-Dist: sphinx-autodoc-typehints>=3.5.2; extra == "all"
Requires-Dist: sphinx-copybutton>=0.5.2; extra == "all"
Requires-Dist: sphinx-design>=0.6.1; extra == "all"
Requires-Dist: sphinx-tabs>=3.4.7; extra == "all"
Requires-Dist: sphinx-togglebutton>=0.3.2; extra == "all"
Requires-Dist: myst-parser>=4.0.1; extra == "all"
Requires-Dist: sphinxcontrib-napoleon>=0.7; extra == "all"
Requires-Dist: doc8>=2.0.0; extra == "all"
Requires-Dist: rstcheck>=6.2.5; extra == "all"
Requires-Dist: Pygments>=2.19.2; extra == "all"
Requires-Dist: docutils>=0.21.2; extra == "all"
Requires-Dist: openpyxl>=3.1.5; extra == "all"
Requires-Dist: seaborn>=0.13.2; extra == "all"
Requires-Dist: plotly>=6.5.0; extra == "all"
Requires-Dist: jinja2>=3.1.6; extra == "all"
Requires-Dist: fastapi>=0.124.0; extra == "all"
Requires-Dist: uvicorn[standard]>=0.38.0; extra == "all"
Requires-Dist: python-multipart>=0.0.20; extra == "all"
Requires-Dist: PyJWT[crypto]>=2.10.0; extra == "all"
Requires-Dist: passlib[bcrypt]>=1.7.4; extra == "all"
Requires-Dist: python-dateutil>=2.9.0.post0; extra == "all"
Requires-Dist: scikit-learn>=1.7.2; extra == "all"
Requires-Dist: statsmodels>=0.14.6; extra == "all"
Requires-Dist: memory-profiler>=0.61.0; extra == "all"
Requires-Dist: line-profiler>=5.0.0; extra == "all"
Requires-Dist: py-spy>=0.4.1; extra == "all"
Requires-Dist: PySide6>=6.10.1; extra == "all"
Requires-Dist: jupyter>=1.1.1; extra == "all"
Requires-Dist: jupyterlab>=4.5.0; extra == "all"
Requires-Dist: ipywidgets>=8.1.8; extra == "all"
Requires-Dist: nbsphinx>=0.9.8; extra == "all"
Requires-Dist: ipykernel>=7.1.0; extra == "all"
Dynamic: license-file
